gdrivepy
