Metadata-Version: 1.1
Name: gdrivepy
Version: 1.8
Summary: Simplest way for using google drive api
Home-page: https://github.com/technicalheist/gdrivepy.git
Author: Technical Heist
Author-email: contact@technicalheist.com
License: MIT
Download-URL: https://github.com/technicalheist/gdrivepy/archive/1.8.tar.gz
Keywords: GOOGLE DRIVE PYTHON,Drive API,Python google drive
Platform: UNKNOWN
Classifier: Development Status :: 4 - Beta
Classifier: Intended Audience :: Developers
Classifier: Topic :: Software Development :: Build Tools
Classifier: License :: OSI Approved :: MIT License
Classifier: Programming Language :: Python :: 3
Classifier: Programming Language :: Python :: 3.4
Classifier: Programming Language :: Python :: 3.5
Classifier: Programming Language :: Python :: 3.6
Classifier: Programming Language :: Python :: 3.7
Classifier: Programming Language :: Python :: 3.8
